batchinfer/__init__.py
batchinfer-0.0.1.dist-info/licenses/LICENSE
batchinfer-0.0.1.dist-info/METADATA
batchinfer-0.0.1.dist-info/WHEEL
batchinfer-0.0.1.dist-info/top_level.txt
batchinfer-0.0.1.dist-info/RECORD
