Metadata-Version: 2.4
Name: batchinfer
Version: 0.0.1
Summary: A batch inference package
Author: AndyXu
License: MIT
Classifier: Programming Language :: Python :: 3
Classifier: License :: OSI Approved :: MIT License
Classifier: Operating System :: OS Independent
Classifier: Topic :: Scientific/Engineering :: Artificial Intelligence
Requires-Python: >=3.7
License-File: LICENSE
Dynamic: license-file
